setup.py
toquen/__init__.py
toquen/client.py
toquen.egg-info/PKG-INFO
toquen.egg-info/SOURCES.txt
toquen.egg-info/dependency_links.txt
toquen.egg-info/requires.txt
toquen.egg-info/top_level.txt