Metadata-Version: 1.1
Name: toquen
Version: 0.2
Summary: Python lib for Toquen: Joins Capistrano + AWS + Chef-Solo into small devops ease
Home-page: http://github.com/bmuller/toquen-python
Author: Brian Muller
Author-email: bamuller@gmail.com
License: MIT
Platform: UNKNOWN
Requires: boto3
